ScryDatasets/__init__.py
ScryDatasets/dataset_info.py
ScryDatasets/dataset_manager.py
ScryDatasets-0.1.0.dist-info/METADATA
ScryDatasets-0.1.0.dist-info/WHEEL
ScryDatasets-0.1.0.dist-info/top_level.txt
ScryDatasets-0.1.0.dist-info/RECORD
