Metadata-Version: 2.1
Name: ScryDatasets
Version: 0.1.0
Summary: A Python library to download datasets created with Scry.
Home-page: https://github.com/sc-govsin/ScryDatasets
Author: Govind Singh
Author-email: govind.singh@scryai.com
Classifier: Programming Language :: Python :: 3
Classifier: Operating System :: OS Independent
Requires-Python: >=3.7
Requires-Dist: PyYAML ==6.0.1
Requires-Dist: pyOpenSSL ==23.3.0
Requires-Dist: pymongo ==3.12.0
Requires-Dist: oci ==2.115.1
Requires-Dist: pandas ==2.2.3
Requires-Dist: tqdm ==4.67.1
